pynoz
