Metadata-Version: 1.1
Name: pynoz
Version: 0.0.9
Summary: simple tools for time date timezone
Home-page: https://github.com/ihgazni2/pynoz
Author: ihgazni2
Author-email: UNKNOWN
License: MIT
Platform: UNKNOWN
Classifier: Environment :: Console
Classifier: Environment :: Web Environment
Classifier: Intended Audience :: End Users/Desktop
Classifier: Intended Audience :: Developers
Classifier: Intended Audience :: System Administrators
Classifier: Programming Language :: Python
